distributed_clients/__init__.py
distributed_clients/distributed_clients/__init__.py
distributed_clients/distributed_clients/arithmetic_rpc.py
distributed_clients/distributed_clients/banking_system.py
distributed_clients/distributed_clients/bully_election.py
distributed_clients/distributed_clients/eventual_consistency.py
distributed_clients/distributed_clients/key_distribution.py
distributed_clients/distributed_clients/load_balancer.py
distributed_clients/distributed_clients/logging_system.py
distributed_clients/distributed_clients/logging_system_easy.py
distributed_clients/distributed_clients/multithreaded_server.py
distributed_clients/distributed_clients/ring_election.py
distributed_clients/distributed_clients/rpc_engine.py
distributed_clients/distributed_clients/rpc_engine_using_eval.py
distributed_clients/distributed_clients/vector_clocks.py
distributed_clients/distributed_computing/1-bank.py
distributed_clients/distributed_computing/10-multithreading-c.py
distributed_clients/distributed_computing/10-multithreading-s.py
distributed_clients/distributed_computing/11-load_balancers.py
distributed_clients/distributed_computing/2-remote-exec-c.py
distributed_clients/distributed_computing/2-remote_exec-s.py
distributed_clients/distributed_computing/3-key-manager.py
distributed_clients/distributed_computing/4-logging.py
distributed_clients/distributed_computing/5-rpc_client.py
distributed_clients/distributed_computing/5-rpc_server.py
distributed_clients/distributed_computing/6-vector_clock.py
distributed_clients/distributed_computing/7-bully.py
distributed_clients/distributed_computing/8-ring.py
distributed_clients/distributed_computing/9-eventual_consistency.py
distributed_clients/distributed_computing/__init__.py
distributed_clients/distributed_servers/server1/__init__.py
distributed_clients/distributed_servers/server1/bank_client.py
distributed_clients/distributed_servers/server1/bank_server.py
distributed_clients/distributed_servers/server10/__init__.py
distributed_clients-0.3.0.dist-info/METADATA
distributed_clients-0.3.0.dist-info/WHEEL
distributed_clients-0.3.0.dist-info/top_level.txt
distributed_clients-0.3.0.dist-info/RECORD
