Metadata-Version: 2.4
Name: distributed-clients
Version: 0.3.0
Requires-Python: >=3.0
Requires-Dist: blinker==1.9.0
Requires-Dist: certifi==2025.11.12
Requires-Dist: charset-normalizer==3.4.4
Requires-Dist: click==8.3.1
Requires-Dist: colorama==0.4.6
Requires-Dist: Flask==3.1.2
Requires-Dist: idna==3.11
Requires-Dist: itsdangerous==2.2.0
Requires-Dist: Jinja2==3.1.6
Requires-Dist: MarkupSafe==3.0.3
Requires-Dist: requests==2.32.5
Requires-Dist: urllib3==2.5.0
Requires-Dist: Werkzeug==3.1.3
